[
	{
		"name": "Settler" , 
		"baseHappiness": 15 ,
		"extraHappinessPerLuxury": 1 ,
		"researchCostModifier": 1 ,
		"unitCostModifier": 1 ,
		"unitSupplyBase": 10 ,
		"unitSupplyPerCity": 0 ,
		"buildingCostModifier": 1 ,
		"policyCostModifier": 1 ,
		"unhappinessModifier": 1 ,
		"barbarianBonus": 1 ,
		"barbarianSpawnDelay": 10 ,
		"playerBonusStartingUnits": [] , // Note that the units from Eras.json are added to this pool. This should only contain bonus starting units.
		"aiCityGrowthModifier": 1 , // that is to say it'll take them 1.6 times as long to grow the city
		"aiUnitCostModifier": 1.5 ,
		"aiBuildingCostModifier": 1.3 ,
		"aiWonderCostModifier": 1.3 ,
		"aiBuildingMaintenanceModifier": 1 ,
		"aiUnitMaintenanceModifier": 1 ,
		"aiUnitSupplyModifier": 0 ,
		"aiFreeTechs": [] ,
		"aiMajorCivBonusStartingUnits": [] ,
		"aiCityStateBonusStartingUnits": [] ,
		"aiUnhappinessModifier": 1 ,
		"aisExchangeTechs": false ,
		"turnBarbariansCanEnterPlayerTiles": 10000 ,
		"clearBarbarianCampReward": 50
	} ,
    {
		"name": "Chieftain" , 
		"baseHappiness": 15 ,
		"extraHappinessPerLuxury": 1 ,
		"researchCostModifier": 1 ,
		"unitCostModifier": 1 ,
		"unitSupplyBase": 10 ,
		"unitSupplyPerCity": 0 ,
		"buildingCostModifier": 1 ,
		"policyCostModifier": 1 ,
		"unhappinessModifier": 1 ,
		"barbarianBonus": 1 ,
		"barbarianSpawnDelay": 10 ,
		"playerBonusStartingUnits": [] , // Note that the units from Eras.json are added to this pool. This should only contain bonus starting units.
		"aiCityGrowthModifier": 1 , // that is to say it'll take them 1.6 times as long to grow the city
		"aiUnitCostModifier": 1.5 ,
		"aiBuildingCostModifier": 1.3 ,
		"aiWonderCostModifier": 1.3 ,
		"aiBuildingMaintenanceModifier": 1 ,
		"aiUnitMaintenanceModifier": 1 ,
		"aiUnitSupplyModifier": 0 ,
		"aiFreeTechs": [] ,
		"aiMajorCivBonusStartingUnits": [] ,
		"aiCityStateBonusStartingUnits": [] ,
		"aiUnhappinessModifier": 1 ,
		"aisExchangeTechs": false ,
		"turnBarbariansCanEnterPlayerTiles": 10000 ,
		"clearBarbarianCampReward": 50
	} ,
    {
		"name": "Warlord" , 
		"baseHappiness": 15 ,
		"extraHappinessPerLuxury": 1 ,
		"researchCostModifier": 1 ,
		"unitCostModifier": 1 ,
		"unitSupplyBase": 10 ,
		"unitSupplyPerCity": 0 ,
		"buildingCostModifier": 1 ,
		"policyCostModifier": 1 ,
		"unhappinessModifier": 1 ,
		"barbarianBonus": 1 ,
		"barbarianSpawnDelay": 10 ,
		"playerBonusStartingUnits": [] , // Note that the units from Eras.json are added to this pool. This should only contain bonus starting units.
		"aiCityGrowthModifier": 1 , // that is to say it'll take them 1.6 times as long to grow the city
		"aiUnitCostModifier": 1.5 ,
		"aiBuildingCostModifier": 1.3 ,
		"aiWonderCostModifier": 1.3 ,
		"aiBuildingMaintenanceModifier": 1 ,
		"aiUnitMaintenanceModifier": 1 ,
		"aiUnitSupplyModifier": 0 ,
		"aiFreeTechs": [] ,
		"aiMajorCivBonusStartingUnits": [] ,
		"aiCityStateBonusStartingUnits": [] ,
		"aiUnhappinessModifier": 1 ,
		"aisExchangeTechs": false ,
		"turnBarbariansCanEnterPlayerTiles": 10000 ,
		"clearBarbarianCampReward": 50
	} ,
    {
		"name": "Prince" ,
		"baseHappiness": 15 ,
		"extraHappinessPerLuxury": 1 ,
		"researchCostModifier": 1 ,
		"unitCostModifier": 1 ,
		"unitSupplyBase": 10 ,
		"unitSupplyPerCity": 0 ,
		"buildingCostModifier": 1 ,
		"policyCostModifier": 1 ,
		"unhappinessModifier": 1 ,
		"barbarianBonus": 1 ,
		"barbarianSpawnDelay": 10 ,
		"playerBonusStartingUnits": [] , // Note that the units from Eras.json are added to this pool. This should only contain bonus starting units.
		"aiCityGrowthModifier": 1 , // that is to say it'll take them 1.6 times as long to grow the city
		"aiUnitCostModifier": 1.5 ,
		"aiBuildingCostModifier": 1.3 ,
		"aiWonderCostModifier": 1.3 ,
		"aiBuildingMaintenanceModifier": 1 ,
		"aiUnitMaintenanceModifier": 1 ,
		"aiUnitSupplyModifier": 0 ,
		"aiFreeTechs": [] ,
		"aiMajorCivBonusStartingUnits": [] ,
		"aiCityStateBonusStartingUnits": [] ,
		"aiUnhappinessModifier": 1 ,
		"aisExchangeTechs": false ,
		"turnBarbariansCanEnterPlayerTiles": 10000 ,
		"clearBarbarianCampReward": 50
	} ,
    {
		"name": "King" , 
		"baseHappiness": 15 ,
		"extraHappinessPerLuxury": 1 ,
		"researchCostModifier": 1 ,
		"unitCostModifier": 1 ,
		"unitSupplyBase": 10 ,
		"unitSupplyPerCity": 0 ,
		"buildingCostModifier": 1 ,
		"policyCostModifier": 1 ,
		"unhappinessModifier": 1 ,
		"barbarianBonus": 1 ,
		"barbarianSpawnDelay": 10 ,
		"playerBonusStartingUnits": [] , // Note that the units from Eras.json are added to this pool. This should only contain bonus starting units.
		"aiCityGrowthModifier": 1 , // that is to say it'll take them 1.6 times as long to grow the city
		"aiUnitCostModifier": 1.5 ,
		"aiBuildingCostModifier": 1.3 ,
		"aiWonderCostModifier": 1.3 ,
		"aiBuildingMaintenanceModifier": 1 ,
		"aiUnitMaintenanceModifier": 1 ,
		"aiUnitSupplyModifier": 0 ,
		"aiFreeTechs": [] ,
		"aiMajorCivBonusStartingUnits": [] ,
		"aiCityStateBonusStartingUnits": [] ,
		"aiUnhappinessModifier": 1 ,
		"aisExchangeTechs": false ,
		"turnBarbariansCanEnterPlayerTiles": 10000 ,
		"clearBarbarianCampReward": 50
	} ,
    {
		"name": "Emperor" , 
		"baseHappiness": 15 ,
		"extraHappinessPerLuxury": 1 ,
		"researchCostModifier": 1 ,
		"unitCostModifier": 1 ,
		"unitSupplyBase": 10 ,
		"unitSupplyPerCity": 0 ,
		"buildingCostModifier": 1 ,
		"policyCostModifier": 1 ,
		"unhappinessModifier": 1 ,
		"barbarianBonus": 1 ,
		"barbarianSpawnDelay": 10 ,
		"playerBonusStartingUnits": [] , // Note that the units from Eras.json are added to this pool. This should only contain bonus starting units.
		"aiCityGrowthModifier": 1 , // that is to say it'll take them 1.6 times as long to grow the city
		"aiUnitCostModifier": 1.5 ,
		"aiBuildingCostModifier": 1.3 ,
		"aiWonderCostModifier": 1.3 ,
		"aiBuildingMaintenanceModifier": 1 ,
		"aiUnitMaintenanceModifier": 1 ,
		"aiUnitSupplyModifier": 0 ,
		"aiFreeTechs": [] ,
		"aiMajorCivBonusStartingUnits": [] ,
		"aiCityStateBonusStartingUnits": [] ,
		"aiUnhappinessModifier": 1 ,
		"aisExchangeTechs": false ,
		"turnBarbariansCanEnterPlayerTiles": 10000 ,
		"clearBarbarianCampReward": 50
	} ,
    {
		"name": "Immortal" , 
		"baseHappiness": 15 ,
		"extraHappinessPerLuxury": 1 ,
		"researchCostModifier": 1 ,
		"unitCostModifier": 1 ,
		"unitSupplyBase": 10 ,
		"unitSupplyPerCity": 0 ,
		"buildingCostModifier": 1 ,
		"policyCostModifier": 1 ,
		"unhappinessModifier": 1 ,
		"barbarianBonus": 1 ,
		"barbarianSpawnDelay": 10 ,
		"playerBonusStartingUnits": [] , // Note that the units from Eras.json are added to this pool. This should only contain bonus starting units.
		"aiCityGrowthModifier": 1 , // that is to say it'll take them 1.6 times as long to grow the city
		"aiUnitCostModifier": 1.5 ,
		"aiBuildingCostModifier": 1.3 ,
		"aiWonderCostModifier": 1.3 ,
		"aiBuildingMaintenanceModifier": 1 ,
		"aiUnitMaintenanceModifier": 1 ,
		"aiUnitSupplyModifier": 0 ,
		"aiFreeTechs": [] ,
		"aiMajorCivBonusStartingUnits": [] ,
		"aiCityStateBonusStartingUnits": [] ,
		"aiUnhappinessModifier": 1 ,
		"aisExchangeTechs": false ,
		"turnBarbariansCanEnterPlayerTiles": 10000 ,
		"clearBarbarianCampReward": 50
	} ,
    {
		"name": "Deity" , 
		"baseHappiness": 15 ,
		"extraHappinessPerLuxury": 1 ,
		"researchCostModifier": 1 ,
		"unitCostModifier": 1 ,
		"unitSupplyBase": 10 ,
		"unitSupplyPerCity": 0 ,
		"buildingCostModifier": 1 ,
		"policyCostModifier": 1 ,
		"unhappinessModifier": 1 ,
		"barbarianBonus": 1 ,
		"barbarianSpawnDelay": 10 ,
		"playerBonusStartingUnits": [] , // Note that the units from Eras.json are added to this pool. This should only contain bonus starting units.
		"aiCityGrowthModifier": 1 , // that is to say it'll take them 1.6 times as long to grow the city
		"aiUnitCostModifier": 1.5 ,
		"aiBuildingCostModifier": 1.3 ,
		"aiWonderCostModifier": 1.3 ,
		"aiBuildingMaintenanceModifier": 1 ,
		"aiUnitMaintenanceModifier": 1 ,
		"aiUnitSupplyModifier": 0 ,
		"aiFreeTechs": [] ,
		"aiMajorCivBonusStartingUnits": [] ,
		"aiCityStateBonusStartingUnits": [] ,
		"aiUnhappinessModifier": 1 ,
		"aisExchangeTechs": false ,
		"turnBarbariansCanEnterPlayerTiles": 10000 ,
		"clearBarbarianCampReward": 50
	}
]